{
    "created_time": "2022-05-25T06:05:08Z",
    "files": [
        {
            "attachment_folder": "",
            "created_time": "2022-05-25T06:05:15Z",
            "id": "15",
            "modified_time": "2022-05-25T06:06:06Z",
            "name": "HomePage.md",
            "signature": "82331881555739",
            "tags": [
            ]
        }
    ],
    "folders": [
    ],
    "id": "14",
    "modified_time": "2022-05-25T06:05:08Z",
    "signature": "113818286802708",
    "version": 3
}
