{
    "created_time": "2022-05-25T12:56:00Z",
    "files": [
        {
            "attachment_folder": "",
            "created_time": "2022-05-25T12:56:25Z",
            "id": "22",
            "modified_time": "2022-05-25T13:35:24Z",
            "name": "HomePage.md",
            "signature": "99992787101561",
            "tags": [
            ]
        }
    ],
    "folders": [
    ],
    "id": "21",
    "modified_time": "2022-05-25T12:56:00Z",
    "signature": "120883508029280",
    "version": 3
}
