{
    "created_time": "2022-06-23T04:14:48Z",
    "files": [
        {
            "attachment_folder": "",
            "created_time": "2022-06-23T04:15:00Z",
            "id": "68",
            "modified_time": "2022-06-23T16:19:42Z",
            "name": "笔记软件测评合集.md",
            "signature": "27205978810564",
            "tags": [
            ]
        }
    ],
    "folders": [
    ],
    "id": "67",
    "modified_time": "2022-06-23T04:14:48Z",
    "signature": "79316817012920",
    "version": 3
}
